odoo/addons/crm_sale_order_line/__init__.py
odoo/addons/crm_sale_order_line/__manifest__.py
odoo/addons/crm_sale_order_line/models/__init__.py
odoo/addons/crm_sale_order_line/models/crm_lead.py
odoo/addons/crm_sale_order_line/models/crm_sale_order_line.py
odoo/addons/crm_sale_order_line/security/ir.model.access.csv
odoo/addons/crm_sale_order_line/views/crm_lead.xml
odoo12_addon_crm_sale_order_line-12.0.0.0.5.dist-info/METADATA
odoo12_addon_crm_sale_order_line-12.0.0.0.5.dist-info/WHEEL
odoo12_addon_crm_sale_order_line-12.0.0.0.5.dist-info/top_level.txt
odoo12_addon_crm_sale_order_line-12.0.0.0.5.dist-info/RECORD
