Metadata-Version: 2.1
Name: odoo12-addon-crm-sale-order-line
Version: 12.0.0.0.5
Summary: Add relationship between crm lead and sale order line
Home-page: 
Author: Coopdevs Treball SCCL
Classifier: Programming Language :: Python
Classifier: Framework :: Odoo
Classifier: Framework :: Odoo :: 12.0
Requires-Python: >=3.5
Requires-Dist: odoo (<12.1dev,>=12.0a)
